selinonlib/__init__.py
selinonlib/builtin_predicate.py
selinonlib/cache_config.py
selinonlib/codename.py
selinonlib/config.py
selinonlib/edge.py
selinonlib/errors.py
selinonlib/failure_node.py
selinonlib/failures.py
selinonlib/flow.py
selinonlib/global_config.py
selinonlib/helpers.py
selinonlib/leaf_predicate.py
selinonlib/node.py
selinonlib/predicate.py
selinonlib/selective_run_function.py
selinonlib/storage.py
selinonlib/strategy.py
selinonlib/system.py
selinonlib/task.py
selinonlib/task_class.py
selinonlib/version.py
selinonlib/caches/__init__.py
selinonlib/caches/fifo.py
selinonlib/caches/lifo.py
selinonlib/caches/lru.py
selinonlib/caches/mru.py
selinonlib/caches/rr.py
selinonlib/migrations/__init__.py
selinonlib/migrations/migrator.py
selinonlib/migrations/tainted_flow_strategy.py
selinonlib/predicates/__init__.py
selinonlib/predicates/alwaysFalse.py
selinonlib/predicates/alwaysTrue.py
selinonlib/predicates/argsEmpty.py
selinonlib/predicates/argsFieldBool.py
selinonlib/predicates/argsFieldContain.py
selinonlib/predicates/argsFieldDict.py
selinonlib/predicates/argsFieldEqual.py
selinonlib/predicates/argsFieldExist.py
selinonlib/predicates/argsFieldFloat.py
selinonlib/predicates/argsFieldGreater.py
selinonlib/predicates/argsFieldGreaterEqual.py
selinonlib/predicates/argsFieldInt.py
selinonlib/predicates/argsFieldLenEqual.py
selinonlib/predicates/argsFieldLenGreater.py
selinonlib/predicates/argsFieldLenGreaterEqual.py
selinonlib/predicates/argsFieldLenLess.py
selinonlib/predicates/argsFieldLenLessEqual.py
selinonlib/predicates/argsFieldLenNotEqual.py
selinonlib/predicates/argsFieldLess.py
selinonlib/predicates/argsFieldLessEqual.py
selinonlib/predicates/argsFieldList.py
selinonlib/predicates/argsFieldNone.py
selinonlib/predicates/argsFieldNotEqual.py
selinonlib/predicates/argsFieldStr.py
selinonlib/predicates/argsFieldUrlNetloc.py
selinonlib/predicates/argsFieldUrlPath.py
selinonlib-1.0.0rc1.dist-info/DESCRIPTION.rst
selinonlib-1.0.0rc1.dist-info/METADATA
selinonlib-1.0.0rc1.dist-info/RECORD
selinonlib-1.0.0rc1.dist-info/WHEEL
selinonlib-1.0.0rc1.dist-info/metadata.json
selinonlib-1.0.0rc1.dist-info/top_level.txt
